{"lastUsed":1619186005178,"path":"D:\/Coding\/Java","projectCount":2,"recentFiles":[{"path":"\/JavaDemos\/src\/variables","parentWorkspace":"D:\/Coding\/Java","name":"Main.java","lastModified":1619186061194,"locationURI":"file:\/D:\/Coding\/Java\/JavaDemos\/src\/variables\/Main.java"},{"path":"\/JavaCamp\/src\/intro","parentWorkspace":"D:\/Coding\/Java","name":"Main.java","lastModified":1619039251548},{"path":"\/JavaDemos\/src\/helloworld","parentWorkspace":"D:\/Coding\/Java","name":"Main.java","lastModified":1619104880054,"locationURI":"file:\/D:\/Coding\/Java\/JavaDemos\/src\/helloworld\/Main.java"}]}